{
    "version": 8,
    "name": "DS site",
    "metadata": {},
    "center": [0,0],
    "zoom": 12,
    "bearing": 0,
    "pitch": 0,
    "sources": {
        "developed_site": {
            "tiles": ["http://localhost/tile_server/ts/developed_site/{z}/{x}/{y}.pbf"],
            "type": "vector"
        }
    },
    "layers": [
        {
            "id": "ds_site_poly",
            "type": "fill",
            "source": "developed_site",
            "source-layer": "boundaries",
            "paint": {
                "fill-color": "hsl(78, 51%, 73%)",
                "fill-opacity": [
                    "interpolate",
                    ["linear"],
                    ["zoom"],
                    5,
                    0,
                    6,
                    0.5
                ]
            }
        },
       
        {
            "id": "ds_site_line",
            "type": "line",
            "source": "developed_site",
            "source-layer": "boundaries",
            "paint": {
                "line-color": "hsl(205, 76%, 70%)",
                "line-width": [
                    "interpolate",
                    ["exponential", 1.3],
                    ["zoom"],
                    8.5,
                    0.1,
                    20,
                    8
                ],
                "line-opacity": [
                    "interpolate",
                    ["linear"],
                    ["zoom"],
                    8,
                    0,
                    8.5,
                    1
                ]
            }
        },


        {
            "id": "ds_site_point",
            "type": "symbol",
            "source": "developed_site",
            "source-layer": "boundaries",
            "paint": {
                "text-color": "hsl(38, 19%, 29%)",
                "text-halo-color": "hsl(0, 0%, 100%)",
                "text-halo-width": 1
            }
        }
        
    ]
}